<?xml version="1.0" encoding="utf-8"?>
<TextureAtlas imagePath="kissy.png">
	<!-- Created with Adobe Animate version 21.0.6.41649 -->
	<!-- http://www.adobe.com/products/animate.html -->
	<SubTexture name="KissyDown0000" x="10" y="10" width="373" height="856"/>
	<SubTexture name="KissyDown0001" x="10" y="10" width="373" height="856"/>
	<SubTexture name="KissyDown0002" x="393" y="10" width="373" height="856"/>
	<SubTexture name="KissyDown0003" x="393" y="10" width="373" height="856"/>
	<SubTexture name="KissyDown0004" x="776" y="10" width="373" height="856"/>
	<SubTexture name="KissyDown0005" x="776" y="10" width="373" height="856"/>
	<SubTexture name="KissyDown0006" x="1159" y="10" width="373" height="856"/>
	<SubTexture name="KissyDown0007" x="1159" y="10" width="373" height="856"/>
	<SubTexture name="KissyDown0008" x="1159" y="10" width="373" height="856"/>
	<SubTexture name="KissyDown0009" x="1159" y="10" width="373" height="856"/>
	<SubTexture name="KissyDown0010" x="1159" y="10" width="373" height="856"/>
	<SubTexture name="KissyIdle0000" x="1542" y="10" width="404" height="857"/>
	<SubTexture name="KissyIdle0001" x="1542" y="10" width="404" height="857"/>
	<SubTexture name="KissyIdle0002" x="1956" y="10" width="404" height="857"/>
	<SubTexture name="KissyIdle0003" x="1956" y="10" width="404" height="857"/>
	<SubTexture name="KissyIdle0004" x="2370" y="10" width="404" height="857"/>
	<SubTexture name="KissyIdle0005" x="2370" y="10" width="404" height="857"/>
	<SubTexture name="KissyIdle0006" x="2784" y="10" width="404" height="857"/>
	<SubTexture name="KissyIdle0007" x="2784" y="10" width="404" height="857"/>
	<SubTexture name="KissyIdle0008" x="3198" y="10" width="404" height="857"/>
	<SubTexture name="KissyIdle0009" x="3198" y="10" width="404" height="857"/>
	<SubTexture name="KissyIdle0010" x="3612" y="10" width="404" height="857"/>
	<SubTexture name="KissyIdle0011" x="3612" y="10" width="404" height="857"/>
	<SubTexture name="KissyIdle0012" x="3612" y="10" width="404" height="857"/>
	<SubTexture name="KissyIdle0013" x="3612" y="10" width="404" height="857"/>
	<SubTexture name="KissyIdle0014" x="3612" y="10" width="404" height="857"/>
	<SubTexture name="KissyIdle0015" x="3612" y="10" width="404" height="857"/>
	<SubTexture name="KissyIdle0016" x="3612" y="10" width="404" height="857"/>
	<SubTexture name="KissyIdle0017" x="3612" y="10" width="404" height="857"/>
	<SubTexture name="KissyIdle0018" x="3612" y="10" width="404" height="857"/>
	<SubTexture name="KissyIdle0019" x="3612" y="10" width="404" height="857"/>
	<SubTexture name="KissyIdle0020" x="3612" y="10" width="404" height="857"/>
	<SubTexture name="KissyIdle0021" x="3612" y="10" width="404" height="857"/>
	<SubTexture name="KissyIdle0022" x="3612" y="10" width="404" height="857"/>
	<SubTexture name="KissyIdle0023" x="3612" y="10" width="404" height="857"/>
	<SubTexture name="KissyLeft0000" x="10" y="877" width="389" height="854"/>
	<SubTexture name="KissyLeft0001" x="10" y="877" width="389" height="854"/>
	<SubTexture name="KissyLeft0002" x="409" y="877" width="389" height="854"/>
	<SubTexture name="KissyLeft0003" x="409" y="877" width="389" height="854"/>
	<SubTexture name="KissyLeft0004" x="808" y="877" width="389" height="854"/>
	<SubTexture name="KissyLeft0005" x="808" y="877" width="389" height="854"/>
	<SubTexture name="KissyLeft0006" x="1207" y="877" width="389" height="854"/>
	<SubTexture name="KissyLeft0007" x="1207" y="877" width="389" height="854"/>
	<SubTexture name="KissyLeft0008" x="1207" y="877" width="389" height="854"/>
	<SubTexture name="KissyLeft0009" x="1207" y="877" width="389" height="854"/>
	<SubTexture name="KissyLeft0010" x="1207" y="877" width="389" height="854"/>
	<SubTexture name="KissyRight0000" x="1606" y="877" width="554" height="854"/>
	<SubTexture name="KissyRight0001" x="1606" y="877" width="554" height="854"/>
	<SubTexture name="KissyRight0002" x="2170" y="877" width="554" height="854"/>
	<SubTexture name="KissyRight0003" x="2170" y="877" width="554" height="854"/>
	<SubTexture name="KissyRight0004" x="2734" y="877" width="554" height="854"/>
	<SubTexture name="KissyRight0005" x="2734" y="877" width="554" height="854"/>
	<SubTexture name="KissyRight0006" x="3298" y="877" width="554" height="854"/>
	<SubTexture name="KissyRight0007" x="3298" y="877" width="554" height="854"/>
	<SubTexture name="KissyRight0008" x="3298" y="877" width="554" height="854"/>
	<SubTexture name="KissyRight0009" x="3298" y="877" width="554" height="854"/>
	<SubTexture name="KissyRight0010" x="10" y="1741" width="554" height="854"/>
	<SubTexture name="KissyUp0000" x="574" y="1741" width="435" height="877"/>
	<SubTexture name="KissyUp0001" x="574" y="1741" width="435" height="877"/>
	<SubTexture name="KissyUp0002" x="1019" y="1741" width="435" height="877"/>
	<SubTexture name="KissyUp0003" x="1019" y="1741" width="435" height="877"/>
	<SubTexture name="KissyUp0004" x="1464" y="1741" width="435" height="877"/>
	<SubTexture name="KissyUp0005" x="1464" y="1741" width="435" height="877"/>
	<SubTexture name="KissyUp0006" x="1909" y="1741" width="435" height="877"/>
	<SubTexture name="KissyUp0007" x="1909" y="1741" width="435" height="877"/>
	<SubTexture name="KissyUp0008" x="1909" y="1741" width="435" height="877"/>
	<SubTexture name="KissyUp0009" x="1909" y="1741" width="435" height="877"/>
	<SubTexture name="KissyUp0010" x="1909" y="1741" width="435" height="877"/>
</TextureAtlas>
